auth.py
exception.py
logger.py
networking.py
setup.cfg
setup.py
asocks.egg-info/PKG-INFO
asocks.egg-info/SOURCES.txt
asocks.egg-info/dependency_links.txt
asocks.egg-info/entry_points.txt
asocks.egg-info/top_level.txt
server/__init__.py
server/__main__.py
server/server_protocol.py