Metadata-Version: 1.1
Name: asocks
Version: 0.1.0
Summary: A SOCKS5 proxy server implementation based on async IO model.
Home-page: https://github.com/nanwu/asocks
Author: Nan Wu
Author-email: nanbytesflow@gmail.com
License: MIT
Keywords: socks,proxy,python3,async
Platform: UNKNOWN
Classifier: Developemnt Status :: 3 - Alpha
Classifier: Programming Language :: Python :: 3.4
Classifier: Programming Language :: Python :: 3.5
